musicmd/__init__.py
musicmd/__main__.py
musicmd/resources/musicgrid.css
musicmd/resources/musicgrid.js
musicmarkdown-0.3.4.dist-info/LICENSE.txt
musicmarkdown-0.3.4.dist-info/METADATA
musicmarkdown-0.3.4.dist-info/WHEEL
musicmarkdown-0.3.4.dist-info/top_level.txt
musicmarkdown-0.3.4.dist-info/RECORD
