Metadata-Version: 2.1
Name: musicmarkdown
Version: 0.3.4
Summary: Makrdown compiler for music grids and structures
Home-page: https://github.com/mpascucci/music_grid_markdown
Author: Marco Pascucci
Author-email: marpas.paris@gmail.com
License: UNKNOWN
Platform: UNKNOWN
Classifier: Programming Language :: Python :: 3
Classifier: Operating System :: OS Independent
